odoo/addons/l10n_it_central_journal_reportlab/README.rst
odoo/addons/l10n_it_central_journal_reportlab/__init__.py
odoo/addons/l10n_it_central_journal_reportlab/__manifest__.py
odoo/addons/l10n_it_central_journal_reportlab/i18n/it.po
odoo/addons/l10n_it_central_journal_reportlab/i18n/l10n_it_central_journal_reportlab.pot
odoo/addons/l10n_it_central_journal_reportlab/models/__init__.py
odoo/addons/l10n_it_central_journal_reportlab/models/account.py
odoo/addons/l10n_it_central_journal_reportlab/readme/CONTRIBUTORS.rst
odoo/addons/l10n_it_central_journal_reportlab/readme/DESCRIPTION.rst
odoo/addons/l10n_it_central_journal_reportlab/security/ir.model.access.csv
odoo/addons/l10n_it_central_journal_reportlab/static/description/icon.png
odoo/addons/l10n_it_central_journal_reportlab/static/description/index.html
odoo/addons/l10n_it_central_journal_reportlab/tests/__init__.py
odoo/addons/l10n_it_central_journal_reportlab/tests/test_central_journal_reportlab.py
odoo/addons/l10n_it_central_journal_reportlab/views/date_range_view.xml
odoo/addons/l10n_it_central_journal_reportlab/wizard/__init__.py
odoo/addons/l10n_it_central_journal_reportlab/wizard/print_giornale.py
odoo/addons/l10n_it_central_journal_reportlab/wizard/print_giornale.xml
odoo14_addon_l10n_it_central_journal_reportlab-14.0.1.2.0.dist-info/METADATA
odoo14_addon_l10n_it_central_journal_reportlab-14.0.1.2.0.dist-info/WHEEL
odoo14_addon_l10n_it_central_journal_reportlab-14.0.1.2.0.dist-info/top_level.txt
odoo14_addon_l10n_it_central_journal_reportlab-14.0.1.2.0.dist-info/RECORD
