Metadata-Version: 2.1
Name: odoo14-addon-l10n_it_central_journal_reportlab
Version: 14.0.1.2.0
Summary: ITA - Libro giornale - Reportlab
Home-page: https://github.com/OCA/l10n-italy
Author: Gianmarco Conte - Dinamiche Aziendali srl, Odoo Community Association (OCA)
Author-email: support@odoo-community.org
License: AGPL-3
Classifier: Programming Language :: Python
Classifier: Framework :: Odoo
Classifier: Framework :: Odoo :: 14.0
Classifier: License :: OSI Approved :: GNU Affero General Public License v3
Classifier: Development Status :: 4 - Beta
Requires-Python: >=3.6
Requires-Dist: odoo14-addon-date-range
Requires-Dist: odoo<14.1dev,>=14.0a
